cipherlink/__init__.py
cipherlink/cipherlink.py
cipherlink-1.0.0.dist-info/LICENCE.txt
cipherlink-1.0.0.dist-info/METADATA
cipherlink-1.0.0.dist-info/WHEEL
cipherlink-1.0.0.dist-info/top_level.txt
cipherlink-1.0.0.dist-info/RECORD
