Metadata-Version: 2.1
Name: cipherlink
Version: 1.0.0
Summary: A Python-based basic ciphering tool library
Author: Ahmet Erdem
Classifier: Programming Language :: Python :: 3
Classifier: License :: OSI Approved :: MIT License
Classifier: Operating System :: OS Independent
Requires-Python: >=3.6
License-File: LICENCE.txt
